nssurge_utils/__init__.py
nssurge_utils/add_to_section.py
nssurge_utils/config.py
nssurge_utils/data/countryFlagsNamesAndDialCodes.json
nssurge_utils/extract_proxy.py
nssurge_utils/parsers.py
nssurge_utils/predicates.py
nssurge_utils/transform.py
nssurge_utils/types.py
nssurge_utils/utils.py
nssurge_utils-0.1.9.dist-info/METADATA
nssurge_utils-0.1.9.dist-info/WHEEL
nssurge_utils-0.1.9.dist-info/entry_points.txt
nssurge_utils-0.1.9.dist-info/RECORD
