Metadata-Version: 2.1
Name: nssurge-utils
Version: 0.1.9
Summary: NSSurge Utilities
Home-page: https://github.com/tddschn/nssurge-utils
License: MIT
Keywords: nssurge,surge,utils
Author: Teddy Xinyuan Chen
Author-email: 45612704+tddschn@users.noreply.github.com
Requires-Python: >=3.11,<4.0
Classifier: License :: OSI Approved :: MIT License
Classifier: Programming Language :: Python :: 3
Classifier: Programming Language :: Python :: 3.11
Classifier: Topic :: Utilities
Project-URL: Bug Tracker, https://github.com/tddschn/nssurge-utils/issues
Project-URL: Repository, https://github.com/tddschn/nssurge-utils
